tests/__init__.py
tests/test_smoke.py
uvicorn_browser/__init__.py
uvicorn_browser/__main__.py
uvicorn_browser/driver.py
uvicorn_browser/main.py
uvicorn_browser/reload.py
uvicorn_browser-0.1.0.dist-info/LICENSE
uvicorn_browser-0.1.0.dist-info/METADATA
uvicorn_browser-0.1.0.dist-info/WHEEL
uvicorn_browser-0.1.0.dist-info/entry_points.txt
uvicorn_browser-0.1.0.dist-info/top_level.txt
uvicorn_browser-0.1.0.dist-info/RECORD
