Metadata-Version: 2.1
Name: uvicorn-browser
Version: 0.1.0
Summary: An awesome package is coming soon! 🎉
Home-page: https://github.com/Kludex/uvicorn-browser
Author: Marcelo Trylesinski
Author-email: marcelotryle@email.com
License: MIT
Project-URL: Twitter, https://twitter.com/marcelotryle
Platform: UNKNOWN
Classifier: License :: OSI Approved :: MIT License
Classifier: Intended Audience :: Developers
Classifier: Natural Language :: English
Classifier: Operating System :: OS Independent
Classifier: Programming Language :: Python :: 3 :: Only
Classifier: Programming Language :: Python :: 3
Classifier: Programming Language :: Python :: 3.6
Classifier: Programming Language :: Python :: 3.7
Classifier: Programming Language :: Python :: 3.8
Classifier: Programming Language :: Python :: 3.9
Classifier: Programming Language :: Python :: 3.10
Classifier: Programming Language :: Python :: Implementation :: CPython
Classifier: Programming Language :: Python :: Implementation :: PyPy
Requires-Python: >=3.8.0
Requires-Dist: uvicorn (==0.16.0)
